<?xml version="1.0" encoding="UTF-8" standalone="yes"?>
<stock>
    <ingredients>
        <entry>
            <key>1</key>
            <value id="1">
                <name>Milk</name>
                <unit>L</unit>
                <category>Liquid</category>
                <price/>
            </value>
        </entry>
        <entry>
            <key>2</key>
            <value id="2">
                <name>Apple</name>
                <unit>kg</unit>
                <category>Fruit</category>
                <price/>
            </value>
        </entry>
    </ingredients>
    <ingredientQuantity/>
</stock>
